antevents/__init__.py
antevents/base.py
antevents/adapters/__init__.py
antevents/adapters/bokeh.py
antevents/adapters/csv.py
antevents/adapters/generic.py
antevents/adapters/influxdb.py
antevents/adapters/mqtt.py
antevents/adapters/mqtt_async.py
antevents/adapters/pandas.py
antevents/adapters/postgres.py
antevents/adapters/tcpstreamer.py
antevents/adapters/rpi/__init__.py
antevents/adapters/rpi/gpio.py
antevents/internal/__init__.py
antevents/internal/basic.py
antevents/linq/__init__.py
antevents/linq/buffer.py
antevents/linq/combinators.py
antevents/linq/dispatch.py
antevents/linq/first.py
antevents/linq/json.py
antevents/linq/map.py
antevents/linq/never.py
antevents/linq/output.py
antevents/linq/scan.py
antevents/linq/select.py
antevents/linq/skip.py
antevents/linq/some.py
antevents/linq/take.py
antevents/linq/timeout.py
antevents/linq/transducer.py
antevents/linq/where.py
antevents/sensors/__init__.py
antevents/sensors/rpi/__init__.py
antevents/sensors/rpi/adxl345_py3.py
antevents/sensors/rpi/arduino.py
antevents/sensors/rpi/gpio.py
antevents/sensors/rpi/lux_sensor.py
antevents/sensors/rpi/sensor.py
antevents-1.1.0.dist-info/DESCRIPTION.rst
antevents-1.1.0.dist-info/METADATA
antevents-1.1.0.dist-info/RECORD
antevents-1.1.0.dist-info/WHEEL
antevents-1.1.0.dist-info/metadata.json
antevents-1.1.0.dist-info/top_level.txt
