Metadata-Version: 2.0
Name: antevents
Version: 1.1.0
Summary: Event Stream processing library for IOT
Home-page: https://github.com/mpi-sws-rse/antevents-python
Author: Jeff Fischer
Author-email: jeff+antevents@data-ken.org
License: Apache 2.0
Keywords: events,iot,sensors
Platform: UNKNOWN
Classifier: Development Status :: 4 - Beta
Classifier: License :: OSI Approved :: Apache Software License
Classifier: Programming Language :: Python :: 3.4
Classifier: Programming Language :: Python :: 3.5
Classifier: Operating System :: OS Independent
Classifier: Intended Audience :: Developers
